Metadata-Version: 2.1
Name: pytest-upload-report
Version: 0.1.0
Summary: pytest-upload-report is a plugin for pytest that upload your test report for test results.
Home-page: https://github.com/tim2anna/pytest-upload-report
Author: Anna
Author-email: 191996155@qq.com
Maintainer: Anna
Maintainer-email: 191996155@qq.com
License: MIT
Keywords: py.test pytest report allure upload
Platform: UNKNOWN
Classifier: Development Status :: 5 - Production/Stable
Classifier: Framework :: Pytest
Classifier: Intended Audience :: Developers
Classifier: Topic :: Software Development :: Testing
Classifier: Programming Language :: Python
Classifier: Programming Language :: Python :: 3
Classifier: Programming Language :: Python :: 3.7
Classifier: Programming Language :: Python :: 3.8
Classifier: Programming Language :: Python :: 3 :: Only
Classifier: Programming Language :: Python :: Implementation :: CPython
Classifier: Programming Language :: Python :: Implementation :: PyPy
Classifier: Operating System :: OS Independent
Classifier: License :: OSI Approved :: MIT License
Requires-Python: >=3.7
License-File: LICENSE
